__init__.py
bbobbenchmarks.py
doe2vec.py
models.py
test_doe2vec.py
modulesRandFunc/NODE.py
modulesRandFunc/__init__.py
modulesRandFunc/generate_exp2fun.py
modulesRandFunc/generate_tree.py
modulesRandFunc/generate_tree2exp.py
doe2vec-0.8.0.dist-info/LICENSE
doe2vec-0.8.0.dist-info/METADATA
doe2vec-0.8.0.dist-info/WHEEL
doe2vec-0.8.0.dist-info/top_level.txt
doe2vec-0.8.0.dist-info/RECORD
