Metadata-Version: 2.1
Name: doe2vec
Version: 0.8.0
Summary: Feature extraction for exploratory landscape analysis
Author-email: Bas van Stein <b.van.stein@liacs.leidenuniv.nl>
License: MIT License        
Project-URL: Homepage, https://github.com/Basvanstein/doe2vec
Keywords: autoencoder,representation learning,exploratory landscape analysis
Classifier: License :: OSI Approved :: MIT License
Classifier: Programming Language :: Python
Classifier: Programming Language :: Python :: 3
Requires-Python: >=3.8
License-File: LICENSE
Requires-Dist: scikit-learn
Requires-Dist: tensorflow
Requires-Dist: matplotlib
Requires-Dist: mlflow
Requires-Dist: pandas
Requires-Dist: huggingface-hub
Requires-Dist: datasets
Provides-Extra: dev
Requires-Dist: black ; extra == 'dev'
Requires-Dist: isort ; extra == 'dev'
Requires-Dist: pip-tools ; extra == 'dev'
